<databaseChangeLog
        xmlns="http://www.liquibase.org/xml/ns/dbchangelog"
        xmlns:xsi="http://www.w3.org/2001/XMLSchema-instance"
        xsi:schemaLocation="http://www.liquibase.org/xml/ns/dbchangelog
                                       http://www.liquibase.org/xml/ns/dbchangelog/dbchangelog-3.5.xsd">

    <changeSet id="init" author="heejeong">
        <createTable tableName="babies">
            <column name="id" type="BIGINT" autoIncrement="true">
                <constraints primaryKey="true" nullable="false"/>
            </column>
            <column name="uuid" type="UUID">
                <constraints nullable="false"/>
            </column>
            <column name="name" type="VARCHAR(100)">
                <constraints nullable="false"/>
            </column>
            <column name="birthdate" type="TIMESTAMP">
                <constraints nullable="false"/>
            </column>
            <column name="is_active" type="BOOLEAN">
                <constraints nullable="true"/>
            </column>
            <column name="created_on" type="TIMESTAMP">
                <constraints nullable="false"/>
            </column>
            <column name="updated_on" type="TIMESTAMP">
                <constraints nullable="false"/>
            </column>
        </createTable>

        <rollback>
            <dropTable tableName="babies"/>
        </rollback>
    </changeSet>
</databaseChangeLog>
